COPYING
README
ez_setup.py
resolver.py
setup.py
resolver.egg-info/PKG-INFO
resolver.egg-info/top_level.txt
