Metadata-Version: 1.0
Name: resolver
Version: 0.1
Summary: Resolve specially formated statements to Python objects.
Home-page: http://lukearno.com/projects/resolver/
Author: Luke Arno
Author-email: luke.arno@gmail.com
License: GPL2
Keywords: import text string eval config
Platform: UNKNOWN
Classifier: Development Status :: 3 - Alpha
Classifier: Intended Audience :: Developers
Classifier: License :: OSI Approved :: GNU General Public License (GPL)
Classifier: Natural Language :: English
Classifier: Operating System :: OS Independent
Classifier: Programming Language :: Python
Classifier: Topic :: Software Development :: Libraries
Classifier: Topic :: Utilities
